deluge_card/__init__.py
deluge_card/deluge_card.py
deluge_card/deluge_kit.py
deluge_card/deluge_sample.py
deluge_card/deluge_song.py
deluge_card/deluge_synth.py
deluge_card/deluge_xml.py
deluge_card/helpers.py
deluge_card-0.7.0.dist-info/LICENSE
deluge_card-0.7.0.dist-info/WHEEL
deluge_card-0.7.0.dist-info/METADATA
deluge_card-0.7.0.dist-info/RECORD
