Metadata-Version: 2.1
Name: deluge-card
Version: 0.7.0
Summary: python api for synthstrom deluge cards from fw3.15+.
Home-page: https://github.com/mupaduw/deluge-card
License: MIT
Author: Chris Chamberlain
Author-email: chrisbc@artisan.co.nz
Requires-Python: >=3.8,<4.0
Classifier: Development Status :: 2 - Pre-Alpha
Classifier: Intended Audience :: Developers
Classifier: License :: OSI Approved :: MIT License
Classifier: Natural Language :: English
Classifier: Programming Language :: Python :: 3
Classifier: Programming Language :: Python :: 3.10
Classifier: Programming Language :: Python :: 3.8
Classifier: Programming Language :: Python :: 3.9
Provides-Extra: dev
Provides-Extra: doc
Provides-Extra: test
Requires-Dist: lxml (>=4.8.0,<5.0.0)
Requires-Dist: pydel (>=0.5.3,<0.6.0)
